django_sidecar/__init__.py
django_sidecar-0.1.0.dist-info/METADATA
django_sidecar-0.1.0.dist-info/WHEEL
django_sidecar-0.1.0.dist-info/top_level.txt
django_sidecar-0.1.0.dist-info/RECORD
