Metadata-Version: 2.1
Name: django_sidecar
Version: 0.1.0
Summary: django sidecar pattern implementation
Home-page: UNKNOWN
Author: svtter
Author-email: svtter@163.com
License: UNKNOWN
Platform: UNKNOWN
